{"version":1,"resource":"file:///Users/miskatammenpaa/repos/hox/packages/server/hoxapp/imports/server/domains/admin/organizationOnboarding/lib/start.lib.ts","entries":[{"id":"PRdy.ts","timestamp":1655384461352},{"id":"ubvj.ts","timestamp":1655385641592},{"id":"ZgR7.ts","timestamp":1655385673123},{"id":"sr1R.ts","timestamp":1655385700313},{"id":"oA5P.ts","timestamp":1655385717156},{"id":"Mpx6.ts","timestamp":1655386077657},{"id":"qzug.ts","timestamp":1655386094269},{"id":"zU0p.ts","timestamp":1655386180675},{"id":"CQRB.ts","timestamp":1655386386248},{"id":"lmIY.ts","timestamp":1655386445968},{"id":"W5mu.ts","source":"Workspace Edit","timestamp":1655386468614},{"id":"vNOR.ts","timestamp":1655387296321},{"id":"CA8G.ts","timestamp":1655387329987},{"id":"MpEi.ts","timestamp":1655387354714},{"id":"GCeS.ts","timestamp":1655387388444},{"id":"AgBX.ts","timestamp":1655387409591},{"id":"LHaI.ts","timestamp":1655387430253},{"id":"eIZM.ts","timestamp":1655387463506},{"id":"Mho6.ts","timestamp":1655387603943},{"id":"lyI7.ts","timestamp":1655387640369},{"id":"AtW6.ts","timestamp":1655387660268},{"id":"XbP5.ts","timestamp":1655387705898},{"id":"180T.ts","timestamp":1655387762207},{"id":"W114.ts","timestamp":1655387824369},{"id":"6yir.ts","timestamp":1655388320734},{"id":"odl1.ts","timestamp":1655388347095},{"id":"StzU.ts","timestamp":1655388460412},{"id":"ety6.ts","timestamp":1655388485078},{"id":"HPnf.ts","timestamp":1655388606749},{"id":"ASzG.ts","timestamp":1655388631407},{"id":"cwNx.ts","timestamp":1655388734718},{"id":"WDGt.ts","timestamp":1655388754221},{"id":"78a0.ts","timestamp":1655388887668},{"id":"l9um.ts","timestamp":1655388929322},{"id":"7Vo1.ts","timestamp":1655389082652},{"id":"yiNM.ts","timestamp":1655389103269},{"id":"y2tO.ts","timestamp":1655450270435},{"id":"SISh.ts","timestamp":1655450627228},{"id":"c6L7.ts","timestamp":1655450648515},{"id":"O4QJ.ts","timestamp":1655450676244},{"id":"RqQu.ts","timestamp":1655451406002},{"id":"qtEK.ts","timestamp":1655453440600},{"id":"X7SI.ts","timestamp":1655453795610},{"id":"MLwV.ts","timestamp":1655453844926},{"id":"oCGG.ts","timestamp":1655453858661},{"id":"DASU.ts","timestamp":1655453868834},{"id":"aa6k.ts","timestamp":1655461319190},{"id":"5p6S.ts","timestamp":1655461450588},{"id":"wvDj.ts","timestamp":1655461964416},{"id":"P5uV.ts","timestamp":1668688122753}]}